{
  "place_id": "ChIJf_v7_CkoRI4R3aeOhwIz11Q",
  "name": "il forno Parque Lleras | Medellín",
  "address": "Cra. 37a #8-9, El Poblado, Medellín, El Poblado, Medellín, Antioquia, Colombia",
  "neighborhood": "El Poblado",
  "lat": 6.2074504,
  "lng": -75.5678686,
  "rating": 4.5,
  "price_level": 2,
  "types": [
    "restaurant"
  ],
  "hours": [
    "lunes: 11:30–15:00, 18:00–20:00",
    "martes: 11:30–15:00, 18:00–20:00",
    "miércoles: 11:30–15:00, 18:00–20:00",
    "jueves: 11:30–20:00",
    "viernes: 11:30–21:00",
    "sábado: 11:30–21:00",
    "domingo: 11:30–19:00"
  ],
  "review_count": 5
}