{
  "place_id": "ChIJJXT6S1KDRo4Rj54z2Fy7lV8",
  "name": "Mistico Bar El Tesoro",
  "address": "Cra. 25a #1a Sur 45, El Poblado, Medellín Modulo 7, Puente occidente El Tesoro Parque Comercial, Bar, segundo nivel, El Poblado, Medellín, El Poblado, Medellín, Antioquia, Colombia",
  "neighborhood": "El Poblado",
  "lat": 6.19794,
  "lng": -75.5590943,
  "rating": 3.6,
  "price_level": null,
  "types": [
    "bar"
  ],
  "hours": [
    "lunes: 12:00–21:00",
    "martes: 12:00–22:00",
    "miércoles: 12:00–22:00",
    "jueves: 10:00–24:00",
    "viernes: 12:00–22:00",
    "sábado: 12:00–22:00",
    "domingo: 12:00–21:00"
  ],
  "review_count": 5
}