{
  "place_id": "ChIJGdMhNigoRI4RWtZNyailQqg",
  "name": "Duque Arango Contemporaneo",
  "address": "Cra. 34 #8a-42, El Poblado, Medellín, El Poblado, Medellín, Antioquia, Colombia",
  "neighborhood": "El Poblado",
  "lat": 6.2082349,
  "lng": -75.5650043,
  "rating": 4.5,
  "price_level": null,
  "types": [
    "art_gallery"
  ],
  "hours": [
    "lunes: 9:00–18:00",
    "martes: 9:00–18:00",
    "miércoles: 9:00–18:00",
    "jueves: 9:00–18:00",
    "viernes: 9:00–17:00",
    "sábado: 9:00–15:30",
    "domingo: Cerrado"
  ],
  "review_count": 5
}